marcobre/__init__.py
marcobre/diff/__init__.py
marcobre/diff/app.py
marcobre/diff/backend/__init__.py
marcobre/diff/backend/algorithm/algorithm.py
marcobre/diff/backend/algorithm/algorithmModels.py
marcobre/diff/backend/algorithm/constants.py
marcobre/diff/backend/backend.py
marcobre/diff/backend/marcobre.db
marcobre/diff/example.py
marcobre/diff/frontend/App.py
marcobre/diff/frontend/ContainerInputFile.py
marcobre/diff/frontend/ContainerInputFileModels.py
marcobre/diff/frontend/MainTable.py
marcobre/diff/frontend/MainTableModels.py
marcobre/diff/frontend/__init__.py
marcobre/diff/frontend/images/logo.png
marcobre/diff/marcobre.spec
marcobre/static/frontend/images/logo.png
marcobre_diff-1.0.3.dist-info/METADATA
marcobre_diff-1.0.3.dist-info/WHEEL
marcobre_diff-1.0.3.dist-info/entry_points.txt
marcobre_diff-1.0.3.dist-info/RECORD
