Metadata-Version: 2.1
Name: marcobre-diff
Version: 1.0.3
Summary: 
Author: glozanoac
Author-email: glozanoac@gmail.com
Requires-Python: >=3.10,<4.0
Classifier: Programming Language :: Python :: 3
Classifier: Programming Language :: Python :: 3.10
Classifier: Programming Language :: Python :: 3.11
Classifier: Programming Language :: Python :: 3.12
Requires-Dist: altgraph (==0.17.4)
Requires-Dist: customtkinter (==5.2.2)
Requires-Dist: darkdetect (==0.8.0)
Requires-Dist: dask (>=2024.11.1,<2025.0.0)
Requires-Dist: ezdxf (>=1.3.4,<2.0.0)
Requires-Dist: matplotlib (>=3.9.2,<4.0.0)
Requires-Dist: numpy (>=2.1.2,<3.0.0)
Requires-Dist: pandas (>=2.2.3,<3.0.0)
Requires-Dist: pillow (==10.4.0)
Requires-Dist: python-dateutil (==2.9.0.post0)
Requires-Dist: pytz (==2024.2)
Requires-Dist: scipy (>=1.14.1,<2.0.0)
Requires-Dist: setuptools (>=75.2.0,<76.0.0)
Requires-Dist: shapely (>=2.0.6,<3.0.0)
Requires-Dist: six (==1.16.0)
Requires-Dist: tzdata (==2024.2)
